{"author":{"id":"MDQ6VXNlcjE0MzE5MDQ=","is_bot":false,"login":"konard","name":"Konstantin Diachenko"},"body":"A downstream repository found a false-positive GitHub Pages deploy caused by using a branch-push deploy action while the repository Pages source was configured for GitHub Actions.\n\nDownstream evidence:\n- Repository: https://github.com/link-assistant/formal-ai\n- Issue: https://github.com/link-assistant/formal-ai/issues/4\n- Failed run: https://github.com/link-assistant/formal-ai/actions/runs/25746871509\n- The deploy job succeeded after running `peaceiris/actions-gh-pages@v4` with `publish_dir: docs/demo` and `publish_branch: gh-pages`.\n- The same run's Pages e2e job failed against the live Pages URL because the expected `.app` root was not served.\n- The repository Pages API returned `build_type: workflow`, so pushing `gh-pages` did not represent the configured Pages deployment path.\n\nTemplate location:\n- `github/workflows/release.yml` has `deploy-docs` using `peaceiris/actions-gh-pages@v4` with `contents: write` and `publish_dir: target/doc`.\n\nReproducible example:\n1. Create a repository from this Rust template.\n2. In repository Settings > Pages, set Build and deployment Source to GitHub Actions.\n3. Run the release workflow path that executes `deploy-docs`.\n4. Observe that `peaceiris/actions-gh-pages` can push the `gh-pages` branch and report success even though no GitHub Actions Pages deployment is created for the workflow-source Pages site.\n5. Add an e2e or smoke check against the live Pages URL; it can fail even though the deploy job passed.\n\nWorkarounds:\n- Configure Pages to deploy from the `gh-pages` branch if keeping `peaceiris/actions-gh-pages`.\n- Or, for repositories configured with GitHub Actions as the Pages source, replace the branch-push deploy with the official Pages artifact flow.\n\nSuggested fix:\nUse the GitHub Pages artifact deployment actions in `deploy-docs`:\n\n```yaml\npermissions:\n  contents: read\n  pages: write\n  id-token: write\n\nenvironment:\n  name: github-pages\n  url: ${{ steps.deployment.outputs.page_url }}\n\nsteps:\n  - uses: actions/checkout@v6\n    with:\n      ref: main\n  - uses: dtolnay/rust-toolchain@stable\n  - run: cargo doc --no-deps --all-features\n  - uses: actions/configure-pages@v6\n  - uses: actions/upload-pages-artifact@v5\n    with:\n      path: target/doc\n  - id: deployment\n    uses: actions/deploy-pages@v5\n```\n\nThis aligns the deploy job with GitHub's custom Pages workflow requirements (`pages: write`, `id-token: write`, `github-pages` environment, uploaded Pages artifact, and a deployment URL output) and makes deployment failures surface in the deploy job instead of only in downstream live-site checks.\n","createdAt":"2026-05-12T16:53:37Z","number":48,"state":"OPEN","title":"GitHub Pages workflow-source repos can get false-positive docs deploys","url":"https://github.com/link-foundation/rust-ai-driven-development-pipeline-template/issues/48"}
