[{"author":{"id":"MDQ6VXNlcjE0MzE5MDQ=","is_bot":false,"login":"konard","name":"Konstantin Diachenko"},"baseRefName":"main","createdAt":"2026-05-18T21:54:40Z","headRefName":"issue-115-f9977aca33fe","isDraft":true,"number":116,"state":"OPEN","title":"[WIP] We need to continue on fully implementing our vision","updatedAt":"2026-05-18T21:54:42Z","url":"https://github.com/link-assistant/formal-ai/pull/116"},{"author":{"id":"MDQ6VXNlcjE0MzE5MDQ=","is_bot":false,"login":"konard","name":"Konstantin Diachenko"},"baseRefName":"main","createdAt":"2026-05-18T20:10:00Z","headRefName":"issue-107-c995aabb2aac","isDraft":false,"number":114,"state":"MERGED","title":"Fix Russian URL requests and browser web search","updatedAt":"2026-05-18T21:39:05Z","url":"https://github.com/link-assistant/formal-ai/pull/114"},{"author":{"id":"MDQ6VXNlcjE0MzE5MDQ=","is_bot":false,"login":"konard","name":"Konstantin Diachenko"},"baseRefName":"main","createdAt":"2026-05-18T16:52:18Z","headRefName":"issue-112-248769046c3f","isDraft":false,"number":113,"state":"MERGED","title":"Improve mobile chat UX and conversation management","updatedAt":"2026-05-18T18:08:08Z","url":"https://github.com/link-assistant/formal-ai/pull/113"},{"author":{"id":"MDQ6VXNlcjE0MzE5MDQ=","is_bot":false,"login":"konard","name":"Konstantin Diachenko"},"baseRefName":"main","createdAt":"2026-05-18T09:58:19Z","headRefName":"issue-110-2af174f3ddb8","isDraft":false,"number":111,"state":"MERGED","title":"Fix mobile keyboard viewport and add UI skin settings","updatedAt":"2026-05-18T10:48:18Z","url":"https://github.com/link-assistant/formal-ai/pull/111"},{"author":{"id":"MDQ6VXNlcjE0MzE5MDQ=","is_bot":false,"login":"konard","name":"Konstantin Diachenko"},"baseRefName":"main","createdAt":"2026-05-18T08:50:26Z","headRefName":"issue-108-e4fa776bf7e7","isDraft":false,"number":109,"state":"MERGED","title":"Improve mobile composer UI and input configuration","updatedAt":"2026-05-18T09:36:24Z","url":"https://github.com/link-assistant/formal-ai/pull/109"},{"author":{"id":"MDQ6VXNlcjE0MzE5MDQ=","is_bot":false,"login":"konard","name":"Konstantin Diachenko"},"baseRefName":"main","createdAt":"2026-05-17T20:00:25Z","headRefName":"issue-105-43de79808581","isDraft":false,"number":106,"state":"MERGED","title":"fix(solver): recognize Russian word-number arithmetic","updatedAt":"2026-05-17T20:22:10Z","url":"https://github.com/link-assistant/formal-ai/pull/106"},{"author":{"id":"MDQ6VXNlcjE0MzE5MDQ=","is_bot":false,"login":"konard","name":"Konstantin Diachenko"},"baseRefName":"main","createdAt":"2026-05-17T12:14:31Z","headRefName":"issue-103-89b7776b0010","isDraft":false,"number":104,"state":"MERGED","title":"Complete issue #103 prompt matrix and production wording","updatedAt":"2026-05-17T19:59:18Z","url":"https://github.com/link-assistant/formal-ai/pull/104"},{"author":{"id":"MDQ6VXNlcjE0MzE5MDQ=","is_bot":false,"login":"konard","name":"Konstantin Diachenko"},"baseRefName":"main","createdAt":"2026-05-17T10:58:23Z","headRefName":"issue-82-1a6565cb42da","isDraft":false,"number":102,"state":"MERGED","title":"Fix typo Wikipedia lookup with assistant settings","updatedAt":"2026-05-17T11:29:05Z","url":"https://github.com/link-assistant/formal-ai/pull/102"},{"author":{"id":"MDQ6VXNlcjE0MzE5MDQ=","is_bot":false,"login":"konard","name":"Konstantin Diachenko"},"baseRefName":"main","createdAt":"2026-05-17T10:50:51Z","headRefName":"issue-64-0f1b4b7009f5","isDraft":false,"number":101,"state":"MERGED","title":"fix: resolve links theory prompts (#64)","updatedAt":"2026-05-17T11:07:11Z","url":"https://github.com/link-assistant/formal-ai/pull/101"},{"author":{"id":"MDQ6VXNlcjE0MzE5MDQ=","is_bot":false,"login":"konard","name":"Konstantin Diachenko"},"baseRefName":"main","createdAt":"2026-05-17T09:38:42Z","headRefName":"issue-93-5c859a5dabc0","isDraft":false,"number":100,"state":"MERGED","title":"Fix combined Russian identity prompts","updatedAt":"2026-05-17T09:53:16Z","url":"https://github.com/link-assistant/formal-ai/pull/100"}]
