{"author":{"id":"MDQ6VXNlcjE0MzE5MDQ=","is_bot":false,"login":"konard","name":"Konstantin Diachenko"},"body":"The best translation is the translation that survives round trip translation.\n\nSo we should by default find such formulation for translation, that is more likely and in most part will survive round trip translation.","createdAt":"2026-06-17T22:19:53Z","number":526,"state":"OPEN","title":"Translation quality test","updatedAt":"2026-06-17T22:19:53Z","url":"https://github.com/link-assistant/formal-ai/issues/526"}
