{
  "entities": {
    "Q309314": {
      "type": "item",
      "id": "Q309314",
      "labels": {
        "en": {
          "language": "en",
          "value": "quantity"
        },
        "ru": {
          "language": "ru",
          "value": "количество"
        },
        "hi": {
          "language": "hi",
          "value": "मात्रा"
        },
        "zh": {
          "language": "zh",
          "value": "量"
        }
      },
      "descriptions": {
        "en": {
          "language": "en",
          "value": "property that exists in a range of magnitudes or multitudes; property that can exist as a magnitude or multitude"
        },
        "ru": {
          "language": "ru",
          "value": "огрубление отношения между сущностями до скалярной величины"
        },
        "zh": {
          "language": "zh",
          "value": "中存在财产范围的大小或众多;属性,可以作为一个大小或存在许多"
        }
      },
      "aliases": {
        "en": [
          {
            "language": "en",
            "value": "amount"
          },
          {
            "language": "en",
            "value": "number"
          },
          {
            "language": "en",
            "value": "quantulum"
          },
          {
            "language": "en",
            "value": "qty"
          }
        ],
        "zh": [
          {
            "language": "zh",
            "value": "數量"
          },
          {
            "language": "zh",
            "value": "数量"
          }
        ]
      }
    }
  },
  "success": 1
}
